package com.cndatacom.e;

public final class e
{
  // ERROR //
  public static boolean a(java.lang.String paramString1, java.lang.String paramString2, java.lang.String paramString3)
  {
    // Byte code:
    //   0: new 14	java/io/File
    //   3: dup
    //   4: aload_0
    //   5: invokespecial 18	java/io/File:<init>	(Ljava/lang/String;)V
    //   8: astore_3
    //   9: aload_3
    //   10: invokevirtual 22	java/io/File:exists	()Z
    //   13: istore 4
    //   15: iconst_0
    //   16: istore 5
    //   18: iload 4
    //   20: ifne +9 -> 29
    //   23: iconst_0
    //   24: istore 5
    //   26: goto +354 -> 380
    //   29: aconst_null
    //   30: astore 6
    //   32: new 24	java/lang/StringBuilder
    //   35: dup
    //   36: invokespecial 27	java/lang/StringBuilder:<init>	()V
    //   39: astore 7
    //   41: aload 7
    //   43: aload_1
    //   44: invokevirtual 31	java/lang/StringBuilder:append	(Ljava/lang/String;)Ljava/lang/StringBuilder;
    //   47: pop
    //   48: aload 7
    //   50: ldc 33
    //   52: invokevirtual 31	java/lang/StringBuilder:append	(Ljava/lang/String;)Ljava/lang/StringBuilder;
    //   55: pop
    //   56: aload 7
    //   58: aload_2
    //   59: invokevirtual 31	java/lang/StringBuilder:append	(Ljava/lang/String;)Ljava/lang/StringBuilder;
    //   62: pop
    //   63: aload 7
    //   65: ldc 35
    //   67: invokevirtual 31	java/lang/StringBuilder:append	(Ljava/lang/String;)Ljava/lang/StringBuilder;
    //   70: pop
    //   71: new 14	java/io/File
    //   74: dup
    //   75: aload 7
    //   77: invokevirtual 39	java/lang/StringBuilder:toString	()Ljava/lang/String;
    //   80: invokespecial 18	java/io/File:<init>	(Ljava/lang/String;)V
    //   83: astore 17
    //   85: aload 17
    //   87: invokevirtual 22	java/io/File:exists	()Z
    //   90: ifeq +9 -> 99
    //   93: aload 17
    //   95: invokevirtual 42	java/io/File:delete	()Z
    //   98: pop
    //   99: aload_3
    //   100: invokevirtual 46	java/io/File:listFiles	()[Ljava/io/File;
    //   103: astore 18
    //   105: aload 18
    //   107: ifnull +225 -> 332
    //   110: aload 18
    //   112: arraylength
    //   113: iconst_1
    //   114: if_icmpge +6 -> 120
    //   117: goto +215 -> 332
    //   120: new 48	java/util/zip/ZipOutputStream
    //   123: dup
    //   124: new 50	java/io/BufferedOutputStream
    //   127: dup
    //   128: new 52	java/io/FileOutputStream
    //   131: dup
    //   132: aload 17
    //   134: invokespecial 55	java/io/FileOutputStream:<init>	(Ljava/io/File;)V
    //   137: invokespecial 58	java/io/BufferedOutputStream:<init>	(Ljava/io/OutputStream;)V
    //   140: invokespecial 59	java/util/zip/ZipOutputStream:<init>	(Ljava/io/OutputStream;)V
    //   143: astore 9
    //   145: sipush 10240
    //   148: newarray byte
    //   150: astore 20
    //   152: aconst_null
    //   153: astore 21
    //   155: iconst_0
    //   156: istore 22
    //   158: iload 22
    //   160: aload 18
    //   162: arraylength
    //   163: if_icmpge +116 -> 279
    //   166: aload 9
    //   168: new 61	java/util/zip/ZipEntry
    //   171: dup
    //   172: aload 18
    //   174: iload 22
    //   176: aaload
    //   177: invokevirtual 64	java/io/File:getName	()Ljava/lang/String;
    //   180: invokespecial 65	java/util/zip/ZipEntry:<init>	(Ljava/lang/String;)V
    //   183: invokevirtual 69	java/util/zip/ZipOutputStream:putNextEntry	(Ljava/util/zip/ZipEntry;)V
    //   186: new 71	java/io/BufferedInputStream
    //   189: dup
    //   190: new 73	java/io/FileInputStream
    //   193: dup
    //   194: aload 18
    //   196: iload 22
    //   198: aaload
    //   199: invokespecial 74	java/io/FileInputStream:<init>	(Ljava/io/File;)V
    //   202: sipush 10240
    //   205: invokespecial 77	java/io/BufferedInputStream:<init>	(Ljava/io/InputStream;I)V
    //   208: astore 23
    //   210: aload 23
    //   212: aload 20
    //   214: iconst_0
    //   215: sipush 10240
    //   218: invokevirtual 81	java/io/BufferedInputStream:read	([BII)I
    //   221: istore 24
    //   223: iload 24
    //   225: iconst_m1
    //   226: if_icmpeq +16 -> 242
    //   229: aload 9
    //   231: aload 20
    //   233: iconst_0
    //   234: iload 24
    //   236: invokevirtual 85	java/util/zip/ZipOutputStream:write	([BII)V
    //   239: goto -29 -> 210
    //   242: iinc 22 1
    //   245: aload 23
    //   247: astore 21
    //   249: goto -91 -> 158
    //   252: astore 10
    //   254: aload 23
    //   256: astore 6
    //   258: goto +181 -> 439
    //   261: astore 12
    //   263: aload 23
    //   265: astore 6
    //   267: goto +132 -> 399
    //   270: astore 8
    //   272: aload 23
    //   274: astore 6
    //   276: goto +142 -> 418
    //   279: aload 21
    //   281: astore 6
    //   283: iconst_1
    //   284: istore 5
    //   286: goto +49 -> 335
    //   289: astore 10
    //   291: aload 21
    //   293: astore 6
    //   295: goto +144 -> 439
    //   298: astore 12
    //   300: aload 21
    //   302: astore 6
    //   304: goto +95 -> 399
    //   307: astore 8
    //   309: aload 21
    //   311: astore 6
    //   313: goto +105 -> 418
    //   316: astore 12
    //   318: aconst_null
    //   319: astore 6
    //   321: goto +78 -> 399
    //   324: astore 8
    //   326: aconst_null
    //   327: astore 6
    //   329: goto +89 -> 418
    //   332: aconst_null
    //   333: astore 9
    //   335: aload 6
    //   337: ifnull +11 -> 348
    //   340: aload 6
    //   342: invokevirtual 88	java/io/BufferedInputStream:close	()V
    //   345: goto +3 -> 348
    //   348: aload 9
    //   350: ifnull +30 -> 380
    //   353: aload 9
    //   355: invokevirtual 89	java/util/zip/ZipOutputStream:close	()V
    //   358: goto +22 -> 380
    //   361: ldc 91
    //   363: aload 19
    //   365: ldc 93
    //   367: invokestatic 98	com/cndatacom/e/j:a	(Ljava/lang/String;Ljava/lang/Exception;Ljava/lang/String;)V
    //   370: new 100	java/lang/RuntimeException
    //   373: dup
    //   374: aload 19
    //   376: invokespecial 103	java/lang/RuntimeException:<init>	(Ljava/lang/Throwable;)V
    //   379: athrow
    //   380: iload 5
    //   382: ireturn
    //   383: astore 10
    //   385: aconst_null
    //   386: astore 9
    //   388: aconst_null
    //   389: astore 6
    //   391: goto +48 -> 439
    //   394: astore 12
    //   396: aconst_null
    //   397: astore 9
    //   399: ldc 91
    //   401: aload 12
    //   403: ldc 105
    //   405: invokestatic 98	com/cndatacom/e/j:a	(Ljava/lang/String;Ljava/lang/Exception;Ljava/lang/String;)V
    //   408: new 100	java/lang/RuntimeException
    //   411: dup
    //   412: aload 12
    //   414: invokespecial 103	java/lang/RuntimeException:<init>	(Ljava/lang/Throwable;)V
    //   417: athrow
    //   418: ldc 91
    //   420: aload 8
    //   422: ldc 107
    //   424: invokestatic 98	com/cndatacom/e/j:a	(Ljava/lang/String;Ljava/lang/Exception;Ljava/lang/String;)V
    //   427: new 100	java/lang/RuntimeException
    //   430: dup
    //   431: aload 8
    //   433: invokespecial 103	java/lang/RuntimeException:<init>	(Ljava/lang/Throwable;)V
    //   436: athrow
    //   437: astore 10
    //   439: aload 6
    //   441: ifnull +11 -> 452
    //   444: aload 6
    //   446: invokevirtual 88	java/io/BufferedInputStream:close	()V
    //   449: goto +3 -> 452
    //   452: aload 9
    //   454: ifnull +30 -> 484
    //   457: aload 9
    //   459: invokevirtual 89	java/util/zip/ZipOutputStream:close	()V
    //   462: goto +22 -> 484
    //   465: ldc 91
    //   467: aload 11
    //   469: ldc 93
    //   471: invokestatic 98	com/cndatacom/e/j:a	(Ljava/lang/String;Ljava/lang/Exception;Ljava/lang/String;)V
    //   474: new 100	java/lang/RuntimeException
    //   477: dup
    //   478: aload 11
    //   480: invokespecial 103	java/lang/RuntimeException:<init>	(Ljava/lang/Throwable;)V
    //   483: athrow
    //   484: aload 10
    //   486: athrow
    //   487: astore 19
    //   489: goto -128 -> 361
    //   492: astore 8
    //   494: aconst_null
    //   495: astore 9
    //   497: aconst_null
    //   498: astore 6
    //   500: goto -82 -> 418
    //   503: astore 11
    //   505: goto -40 -> 465
    //
    // Exception table:
    //   from	to	target	type
    //   210	239	252	finally
    //   210	239	261	java/io/IOException
    //   210	239	270	java/io/FileNotFoundException
    //   158	210	289	finally
    //   158	210	298	java/io/IOException
    //   158	210	307	java/io/FileNotFoundException
    //   145	152	316	java/io/IOException
    //   145	152	324	java/io/FileNotFoundException
    //   32	145	383	finally
    //   32	145	394	java/io/IOException
    //   145	152	437	finally
    //   399	437	437	finally
    //   340	358	487	java/lang/Exception
    //   32	145	492	java/io/FileNotFoundException
    //   444	462	503	java/lang/Exception
  }
}

/* Location:           C:\Users\bbbff\Desktop\onekey-decompile-apk\_tools\dex2jar\source-3125444_dex2jar.jar
 * Qualified Name:     com.cndatacom.e.e
 * JD-Core Version:    0.6.1
 */