package com.qihoo.jiagu;

import com.qihoo.bugreport.javacrash.ExceptionHandleReporter;
import org.json.JSONObject;

public final class e extends Thread
{
  public e(ExceptionHandleReporter paramExceptionHandleReporter, boolean paramBoolean, JSONObject paramJSONObject)
  {
  }

  // ERROR //
  public final void run()
  {
    // Byte code:
    //   0: aload_0
    //   1: getfield 14	com/qihoo/jiagu/e:c	Lcom/qihoo/bugreport/javacrash/ExceptionHandleReporter;
    //   4: invokestatic 35	com/qihoo/bugreport/javacrash/ExceptionHandleReporter:a	(Lcom/qihoo/bugreport/javacrash/ExceptionHandleReporter;)Landroid/content/Context;
    //   7: astore_2
    //   8: aload_2
    //   9: ldc 37
    //   11: invokestatic 42	com/qihoo/jiagu/c:a	(Landroid/content/Context;Ljava/lang/String;)Z
    //   14: ifeq +572 -> 586
    //   17: aload_2
    //   18: ldc 44
    //   20: invokevirtual 50	android/content/Context:getSystemService	(Ljava/lang/String;)Ljava/lang/Object;
    //   23: checkcast 52	android/net/ConnectivityManager
    //   26: iconst_1
    //   27: invokevirtual 56	android/net/ConnectivityManager:getNetworkInfo	(I)Landroid/net/NetworkInfo;
    //   30: invokevirtual 62	android/net/NetworkInfo:isConnected	()Z
    //   33: ifeq +548 -> 581
    //   36: iconst_1
    //   37: istore_3
    //   38: aload_0
    //   39: getfield 16	com/qihoo/jiagu/e:a	Z
    //   42: ifne +1033 -> 1075
    //   45: aload_0
    //   46: getfield 14	com/qihoo/jiagu/e:c	Lcom/qihoo/bugreport/javacrash/ExceptionHandleReporter;
    //   49: invokestatic 35	com/qihoo/bugreport/javacrash/ExceptionHandleReporter:a	(Lcom/qihoo/bugreport/javacrash/ExceptionHandleReporter;)Landroid/content/Context;
    //   52: ldc 64
    //   54: invokestatic 66	com/qihoo/jiagu/c:c	(Landroid/content/Context;Ljava/lang/String;)Z
    //   57: istore 4
    //   59: goto +1019 -> 1078
    //   62: new 68	com/qihoo/jiagu/d
    //   65: dup
    //   66: invokespecial 69	com/qihoo/jiagu/d:<init>	()V
    //   69: pop
    //   70: aload_0
    //   71: getfield 18	com/qihoo/jiagu/e:b	Lorg/json/JSONObject;
    //   74: astore 6
    //   76: aload 6
    //   78: ifnull +502 -> 580
    //   81: aload 6
    //   83: invokevirtual 75	org/json/JSONObject:toString	()Ljava/lang/String;
    //   86: astore 7
    //   88: aload 7
    //   90: invokevirtual 81	java/lang/String:length	()I
    //   93: ifeq +487 -> 580
    //   96: getstatic 87	android/os/Build$VERSION:SDK_INT	I
    //   99: bipush 8
    //   101: if_icmplt +479 -> 580
    //   104: new 89	java/io/ByteArrayOutputStream
    //   107: dup
    //   108: invokespecial 90	java/io/ByteArrayOutputStream:<init>	()V
    //   111: astore 8
    //   113: new 92	java/util/zip/GZIPOutputStream
    //   116: dup
    //   117: aload 8
    //   119: invokespecial 95	java/util/zip/GZIPOutputStream:<init>	(Ljava/io/OutputStream;)V
    //   122: astore 9
    //   124: aload 9
    //   126: aload 7
    //   128: invokevirtual 99	java/lang/String:getBytes	()[B
    //   131: invokevirtual 103	java/util/zip/GZIPOutputStream:write	([B)V
    //   134: aload 9
    //   136: invokevirtual 106	java/util/zip/GZIPOutputStream:flush	()V
    //   139: aload 9
    //   141: invokevirtual 109	java/util/zip/GZIPOutputStream:close	()V
    //   144: aload 8
    //   146: invokevirtual 112	java/io/ByteArrayOutputStream:toByteArray	()[B
    //   149: astore 10
    //   151: bipush 16
    //   153: newarray byte
    //   155: astore 11
    //   157: new 114	java/util/Random
    //   160: dup
    //   161: invokespecial 115	java/util/Random:<init>	()V
    //   164: aload 11
    //   166: invokevirtual 118	java/util/Random:nextBytes	([B)V
    //   169: ldc 120
    //   171: invokestatic 126	javax/crypto/Cipher:getInstance	(Ljava/lang/String;)Ljavax/crypto/Cipher;
    //   174: astore 12
    //   176: aload 12
    //   178: iconst_1
    //   179: new 128	javax/crypto/spec/SecretKeySpec
    //   182: dup
    //   183: aload 11
    //   185: ldc 120
    //   187: invokespecial 131	javax/crypto/spec/SecretKeySpec:<init>	([BLjava/lang/String;)V
    //   190: invokevirtual 135	javax/crypto/Cipher:init	(ILjava/security/Key;)V
    //   193: aload 12
    //   195: aload 10
    //   197: invokevirtual 139	javax/crypto/Cipher:update	([B)[B
    //   200: astore 13
    //   202: iconst_4
    //   203: bipush 16
    //   205: aload 13
    //   207: arraylength
    //   208: iadd
    //   209: iadd
    //   210: newarray byte
    //   212: astore 14
    //   214: iconst_4
    //   215: newarray byte
    //   217: astore 15
    //   219: aload 15
    //   221: iconst_0
    //   222: bipush 16
    //   224: bastore
    //   225: aload 15
    //   227: iconst_1
    //   228: iconst_0
    //   229: i2b
    //   230: bastore
    //   231: aload 15
    //   233: iconst_2
    //   234: iconst_0
    //   235: i2b
    //   236: bastore
    //   237: aload 15
    //   239: iconst_3
    //   240: iconst_0
    //   241: i2b
    //   242: bastore
    //   243: aload 15
    //   245: iconst_0
    //   246: aload 14
    //   248: iconst_0
    //   249: iconst_4
    //   250: invokestatic 145	java/lang/System:arraycopy	(Ljava/lang/Object;ILjava/lang/Object;II)V
    //   253: aload 11
    //   255: iconst_0
    //   256: aload 14
    //   258: iconst_4
    //   259: bipush 16
    //   261: invokestatic 145	java/lang/System:arraycopy	(Ljava/lang/Object;ILjava/lang/Object;II)V
    //   264: aload 13
    //   266: iconst_0
    //   267: aload 14
    //   269: bipush 20
    //   271: aload 13
    //   273: arraylength
    //   274: invokestatic 145	java/lang/System:arraycopy	(Ljava/lang/Object;ILjava/lang/Object;II)V
    //   277: aload 14
    //   279: iconst_0
    //   280: invokestatic 151	android/util/Base64:encodeToString	([BI)Ljava/lang/String;
    //   283: astore 16
    //   285: aload 16
    //   287: ldc 153
    //   289: invokestatic 159	java/net/URLEncoder:encode	(Ljava/lang/String;Ljava/lang/String;)Ljava/lang/String;
    //   292: astore 17
    //   294: aload 17
    //   296: invokevirtual 99	java/lang/String:getBytes	()[B
    //   299: invokestatic 162	com/qihoo/jiagu/c:a	([B)Ljava/lang/String;
    //   302: astore 18
    //   304: aload 18
    //   306: ifnonnull +285 -> 591
    //   309: aconst_null
    //   310: astore 23
    //   312: iload_3
    //   313: ifeq +247 -> 560
    //   316: new 39	com/qihoo/jiagu/c
    //   319: dup
    //   320: invokespecial 163	com/qihoo/jiagu/c:<init>	()V
    //   323: pop
    //   324: new 165	org/apache/http/client/methods/HttpPost
    //   327: dup
    //   328: invokestatic 169	com/qihoo/jiagu/b:a	()Ljava/lang/String;
    //   331: invokespecial 172	org/apache/http/client/methods/HttpPost:<init>	(Ljava/lang/String;)V
    //   334: astore 25
    //   336: aload 25
    //   338: ldc 174
    //   340: ldc 176
    //   342: invokevirtual 180	org/apache/http/client/methods/HttpPost:addHeader	(Ljava/lang/String;Ljava/lang/String;)V
    //   345: aload 25
    //   347: ldc 182
    //   349: ldc 184
    //   351: invokevirtual 180	org/apache/http/client/methods/HttpPost:addHeader	(Ljava/lang/String;Ljava/lang/String;)V
    //   354: aload 25
    //   356: ldc 186
    //   358: ldc 188
    //   360: invokevirtual 180	org/apache/http/client/methods/HttpPost:addHeader	(Ljava/lang/String;Ljava/lang/String;)V
    //   363: new 190	org/apache/http/params/BasicHttpParams
    //   366: dup
    //   367: invokespecial 191	org/apache/http/params/BasicHttpParams:<init>	()V
    //   370: astore 26
    //   372: aload 26
    //   374: invokestatic 193	com/qihoo/jiagu/b:b	()I
    //   377: invokestatic 199	org/apache/http/params/HttpConnectionParams:setConnectionTimeout	(Lorg/apache/http/params/HttpParams;I)V
    //   380: aload 26
    //   382: invokestatic 201	com/qihoo/jiagu/b:c	()I
    //   385: invokestatic 204	org/apache/http/params/HttpConnectionParams:setSoTimeout	(Lorg/apache/http/params/HttpParams;I)V
    //   388: new 206	org/apache/http/impl/client/DefaultHttpClient
    //   391: dup
    //   392: aload 26
    //   394: invokespecial 209	org/apache/http/impl/client/DefaultHttpClient:<init>	(Lorg/apache/http/params/HttpParams;)V
    //   397: astore 27
    //   399: new 211	java/util/ArrayList
    //   402: dup
    //   403: iconst_2
    //   404: invokespecial 214	java/util/ArrayList:<init>	(I)V
    //   407: astore 28
    //   409: aload 28
    //   411: new 216	org/apache/http/message/BasicNameValuePair
    //   414: dup
    //   415: ldc 217
    //   417: aload 16
    //   419: invokespecial 219	org/apache/http/message/BasicNameValuePair:<init>	(Ljava/lang/String;Ljava/lang/String;)V
    //   422: invokeinterface 225 2 0
    //   427: pop
    //   428: aload 28
    //   430: new 216	org/apache/http/message/BasicNameValuePair
    //   433: dup
    //   434: ldc 227
    //   436: aload 23
    //   438: invokespecial 219	org/apache/http/message/BasicNameValuePair:<init>	(Ljava/lang/String;Ljava/lang/String;)V
    //   441: invokeinterface 225 2 0
    //   446: pop
    //   447: invokestatic 232	com/qihoo/bugreport/CrashReport:a	()Landroid/content/Context;
    //   450: ldc 234
    //   452: invokestatic 66	com/qihoo/jiagu/c:c	(Landroid/content/Context;Ljava/lang/String;)Z
    //   455: istore 31
    //   457: iload 31
    //   459: ifeq +25 -> 484
    //   462: ldc 236
    //   464: new 238	java/lang/StringBuilder
    //   467: dup
    //   468: ldc 240
    //   470: invokespecial 241	java/lang/StringBuilder:<init>	(Ljava/lang/String;)V
    //   473: aload 16
    //   475: invokevirtual 245	java/lang/StringBuilder:append	(Ljava/lang/String;)Ljava/lang/StringBuilder;
    //   478: invokevirtual 246	java/lang/StringBuilder:toString	()Ljava/lang/String;
    //   481: invokestatic 250	com/qihoo/jiagu/f:a	(Ljava/lang/String;Ljava/lang/String;)V
    //   484: aload 25
    //   486: new 252	org/apache/http/client/entity/UrlEncodedFormEntity
    //   489: dup
    //   490: aload 28
    //   492: invokespecial 255	org/apache/http/client/entity/UrlEncodedFormEntity:<init>	(Ljava/util/List;)V
    //   495: invokevirtual 259	org/apache/http/client/methods/HttpPost:setEntity	(Lorg/apache/http/HttpEntity;)V
    //   498: aload 27
    //   500: aload 25
    //   502: invokeinterface 265 2 0
    //   507: astore 56
    //   509: aload 56
    //   511: invokeinterface 271 1 0
    //   516: invokeinterface 276 1 0
    //   521: pop
    //   522: iload 31
    //   524: ifeq +36 -> 560
    //   527: ldc 236
    //   529: new 238	java/lang/StringBuilder
    //   532: dup
    //   533: ldc_w 278
    //   536: invokespecial 241	java/lang/StringBuilder:<init>	(Ljava/lang/String;)V
    //   539: aload 56
    //   541: invokeinterface 271 1 0
    //   546: invokeinterface 276 1 0
    //   551: invokevirtual 281	java/lang/StringBuilder:append	(I)Ljava/lang/StringBuilder;
    //   554: invokevirtual 246	java/lang/StringBuilder:toString	()Ljava/lang/String;
    //   557: invokestatic 250	com/qihoo/jiagu/f:a	(Ljava/lang/String;Ljava/lang/String;)V
    //   560: iload 4
    //   562: ifeq +18 -> 580
    //   565: aload 6
    //   567: ifnull +13 -> 580
    //   570: aload 17
    //   572: ifnull +8 -> 580
    //   575: aload 23
    //   577: ifnonnull +109 -> 686
    //   580: return
    //   581: iconst_0
    //   582: istore_3
    //   583: goto -545 -> 38
    //   586: iconst_0
    //   587: istore_3
    //   588: goto -550 -> 38
    //   591: aload 18
    //   593: invokevirtual 99	java/lang/String:getBytes	()[B
    //   596: astore 19
    //   598: bipush 16
    //   600: newarray byte
    //   602: astore 20
    //   604: bipush 48
    //   606: newarray byte
    //   608: astore 21
    //   610: new 114	java/util/Random
    //   613: dup
    //   614: invokespecial 115	java/util/Random:<init>	()V
    //   617: aload 20
    //   619: invokevirtual 118	java/util/Random:nextBytes	([B)V
    //   622: aload 20
    //   624: invokestatic 162	com/qihoo/jiagu/c:a	([B)Ljava/lang/String;
    //   627: invokevirtual 99	java/lang/String:getBytes	()[B
    //   630: astore 22
    //   632: aload 19
    //   634: bipush 16
    //   636: aload 21
    //   638: iconst_0
    //   639: bipush 16
    //   641: invokestatic 145	java/lang/System:arraycopy	(Ljava/lang/Object;ILjava/lang/Object;II)V
    //   644: aload 22
    //   646: iconst_0
    //   647: aload 21
    //   649: bipush 16
    //   651: bipush 16
    //   653: invokestatic 145	java/lang/System:arraycopy	(Ljava/lang/Object;ILjava/lang/Object;II)V
    //   656: aload 19
    //   658: iconst_0
    //   659: aload 21
    //   661: bipush 32
    //   663: bipush 16
    //   665: invokestatic 145	java/lang/System:arraycopy	(Ljava/lang/Object;ILjava/lang/Object;II)V
    //   668: new 77	java/lang/String
    //   671: dup
    //   672: aload 21
    //   674: invokespecial 283	java/lang/String:<init>	([B)V
    //   677: astore 23
    //   679: goto -367 -> 312
    //   682: astore_1
    //   683: goto -103 -> 580
    //   686: aload 6
    //   688: getstatic 289	com/qihoo/bugreport/javacrash/ReportField:ct	Lcom/qihoo/bugreport/javacrash/ReportField;
    //   691: invokevirtual 292	com/qihoo/bugreport/javacrash/ReportField:name	()Ljava/lang/String;
    //   694: invokevirtual 296	org/json/JSONObject:has	(Ljava/lang/String;)Z
    //   697: ifeq -117 -> 580
    //   700: invokestatic 232	com/qihoo/bugreport/CrashReport:a	()Landroid/content/Context;
    //   703: invokevirtual 300	android/content/Context:getFilesDir	()Ljava/io/File;
    //   706: invokevirtual 305	java/io/File:getAbsolutePath	()Ljava/lang/String;
    //   709: astore 35
    //   711: new 302	java/io/File
    //   714: dup
    //   715: new 238	java/lang/StringBuilder
    //   718: dup
    //   719: invokespecial 306	java/lang/StringBuilder:<init>	()V
    //   722: aload 35
    //   724: invokevirtual 245	java/lang/StringBuilder:append	(Ljava/lang/String;)Ljava/lang/StringBuilder;
    //   727: ldc_w 308
    //   730: invokevirtual 245	java/lang/StringBuilder:append	(Ljava/lang/String;)Ljava/lang/StringBuilder;
    //   733: invokevirtual 246	java/lang/StringBuilder:toString	()Ljava/lang/String;
    //   736: invokespecial 309	java/io/File:<init>	(Ljava/lang/String;)V
    //   739: astore 36
    //   741: aload 36
    //   743: invokevirtual 312	java/io/File:exists	()Z
    //   746: ifne +41 -> 787
    //   749: aload 36
    //   751: invokevirtual 315	java/io/File:isDirectory	()Z
    //   754: ifne +33 -> 787
    //   757: aload 36
    //   759: invokevirtual 318	java/io/File:mkdirs	()Z
    //   762: pop
    //   763: new 238	java/lang/StringBuilder
    //   766: dup
    //   767: ldc_w 320
    //   770: invokespecial 241	java/lang/StringBuilder:<init>	(Ljava/lang/String;)V
    //   773: aload 36
    //   775: invokevirtual 305	java/io/File:getAbsolutePath	()Ljava/lang/String;
    //   778: invokevirtual 245	java/lang/StringBuilder:append	(Ljava/lang/String;)Ljava/lang/StringBuilder;
    //   781: invokevirtual 246	java/lang/StringBuilder:toString	()Ljava/lang/String;
    //   784: invokestatic 322	com/qihoo/jiagu/d:a	(Ljava/lang/String;)V
    //   787: new 324	java/lang/StringBuffer
    //   790: dup
    //   791: invokespecial 325	java/lang/StringBuffer:<init>	()V
    //   794: astore 37
    //   796: aload 37
    //   798: ldc_w 327
    //   801: invokevirtual 330	java/lang/StringBuffer:append	(Ljava/lang/String;)Ljava/lang/StringBuffer;
    //   804: ldc_w 332
    //   807: invokevirtual 330	java/lang/StringBuffer:append	(Ljava/lang/String;)Ljava/lang/StringBuffer;
    //   810: aload 17
    //   812: invokevirtual 330	java/lang/StringBuffer:append	(Ljava/lang/String;)Ljava/lang/StringBuffer;
    //   815: ldc_w 334
    //   818: invokevirtual 330	java/lang/StringBuffer:append	(Ljava/lang/String;)Ljava/lang/StringBuffer;
    //   821: aload 23
    //   823: invokevirtual 330	java/lang/StringBuffer:append	(Ljava/lang/String;)Ljava/lang/StringBuffer;
    //   826: pop
    //   827: ldc 68
    //   829: monitorenter
    //   830: aload 6
    //   832: getstatic 289	com/qihoo/bugreport/javacrash/ReportField:ct	Lcom/qihoo/bugreport/javacrash/ReportField;
    //   835: invokevirtual 292	com/qihoo/bugreport/javacrash/ReportField:name	()Ljava/lang/String;
    //   838: invokevirtual 338	org/json/JSONObject:getString	(Ljava/lang/String;)Ljava/lang/String;
    //   841: astore 41
    //   843: new 340	java/text/SimpleDateFormat
    //   846: dup
    //   847: ldc_w 342
    //   850: getstatic 348	java/util/Locale:ENGLISH	Ljava/util/Locale;
    //   853: invokespecial 351	java/text/SimpleDateFormat:<init>	(Ljava/lang/String;Ljava/util/Locale;)V
    //   856: aload 41
    //   858: invokevirtual 355	java/text/SimpleDateFormat:parse	(Ljava/lang/String;)Ljava/util/Date;
    //   861: invokevirtual 361	java/util/Date:getTime	()J
    //   864: lstore 42
    //   866: new 302	java/io/File
    //   869: dup
    //   870: new 238	java/lang/StringBuilder
    //   873: dup
    //   874: invokespecial 306	java/lang/StringBuilder:<init>	()V
    //   877: aload 36
    //   879: invokevirtual 364	java/lang/StringBuilder:append	(Ljava/lang/Object;)Ljava/lang/StringBuilder;
    //   882: ldc_w 366
    //   885: invokevirtual 245	java/lang/StringBuilder:append	(Ljava/lang/String;)Ljava/lang/StringBuilder;
    //   888: lload 42
    //   890: invokestatic 370	java/lang/String:valueOf	(J)Ljava/lang/String;
    //   893: invokevirtual 245	java/lang/StringBuilder:append	(Ljava/lang/String;)Ljava/lang/StringBuilder;
    //   896: invokevirtual 246	java/lang/StringBuilder:toString	()Ljava/lang/String;
    //   899: invokespecial 309	java/io/File:<init>	(Ljava/lang/String;)V
    //   902: astore 44
    //   904: new 372	java/io/FileOutputStream
    //   907: dup
    //   908: aload 44
    //   910: invokespecial 375	java/io/FileOutputStream:<init>	(Ljava/io/File;)V
    //   913: astore 45
    //   915: aload 45
    //   917: aload 37
    //   919: invokevirtual 376	java/lang/StringBuffer:toString	()Ljava/lang/String;
    //   922: invokevirtual 99	java/lang/String:getBytes	()[B
    //   925: invokevirtual 377	java/io/FileOutputStream:write	([B)V
    //   928: aload 45
    //   930: invokevirtual 378	java/io/FileOutputStream:flush	()V
    //   933: aload 45
    //   935: invokevirtual 379	java/io/FileOutputStream:close	()V
    //   938: new 238	java/lang/StringBuilder
    //   941: dup
    //   942: ldc_w 320
    //   945: invokespecial 241	java/lang/StringBuilder:<init>	(Ljava/lang/String;)V
    //   948: aload 44
    //   950: invokevirtual 305	java/io/File:getAbsolutePath	()Ljava/lang/String;
    //   953: invokevirtual 245	java/lang/StringBuilder:append	(Ljava/lang/String;)Ljava/lang/StringBuilder;
    //   956: invokevirtual 246	java/lang/StringBuilder:toString	()Ljava/lang/String;
    //   959: invokestatic 322	com/qihoo/jiagu/d:a	(Ljava/lang/String;)V
    //   962: ldc 68
    //   964: monitorexit
    //   965: goto -385 -> 580
    //   968: astore 40
    //   970: ldc 68
    //   972: monitorexit
    //   973: aload 40
    //   975: athrow
    //   976: astore 34
    //   978: goto -398 -> 580
    //   981: astore 39
    //   983: ldc 68
    //   985: monitorexit
    //   986: goto -406 -> 580
    //   989: astore 54
    //   991: aconst_null
    //   992: astore 45
    //   994: aload 45
    //   996: ifnull +8 -> 1004
    //   999: aload 45
    //   1001: invokevirtual 379	java/io/FileOutputStream:close	()V
    //   1004: ldc 68
    //   1006: monitorexit
    //   1007: goto -427 -> 580
    //   1010: astore 53
    //   1012: aload 53
    //   1014: astore 49
    //   1016: aconst_null
    //   1017: astore 50
    //   1019: aload 50
    //   1021: ifnull +8 -> 1029
    //   1024: aload 50
    //   1026: invokevirtual 379	java/io/FileOutputStream:close	()V
    //   1029: aload 49
    //   1031: athrow
    //   1032: astore 52
    //   1034: goto -96 -> 938
    //   1037: astore 47
    //   1039: goto -35 -> 1004
    //   1042: astore 51
    //   1044: goto -15 -> 1029
    //   1047: astore 48
    //   1049: aload 48
    //   1051: astore 49
    //   1053: aload 45
    //   1055: astore 50
    //   1057: goto -38 -> 1019
    //   1060: astore 46
    //   1062: goto -68 -> 994
    //   1065: astore 33
    //   1067: goto -507 -> 560
    //   1070: astore 32
    //   1072: goto -574 -> 498
    //   1075: iconst_0
    //   1076: istore 4
    //   1078: iload_3
    //   1079: ifne -1017 -> 62
    //   1082: iload 4
    //   1084: ifeq -504 -> 580
    //   1087: goto -1025 -> 62
    //
    // Exception table:
    //   from	to	target	type
    //   0	484	682	java/lang/Throwable
    //   484	498	682	java/lang/Throwable
    //   498	560	682	java/lang/Throwable
    //   591	679	682	java/lang/Throwable
    //   830	866	968	finally
    //   866	904	968	finally
    //   933	938	968	finally
    //   938	973	968	finally
    //   983	986	968	finally
    //   999	1004	968	finally
    //   1004	1007	968	finally
    //   1024	1029	968	finally
    //   1029	1032	968	finally
    //   686	830	976	java/lang/Throwable
    //   973	976	976	java/lang/Throwable
    //   830	866	981	java/lang/Exception
    //   904	915	989	java/lang/Exception
    //   904	915	1010	finally
    //   933	938	1032	java/io/IOException
    //   999	1004	1037	java/io/IOException
    //   1024	1029	1042	java/io/IOException
    //   915	933	1047	finally
    //   915	933	1060	java/lang/Exception
    //   498	560	1065	java/io/IOException
    //   484	498	1070	java/io/UnsupportedEncodingException
  }
}

/* Location:           C:\Users\bbbff\Desktop\onekey-decompile-apk\_tools\dex2jar\source-3125444_dex2jar.jar
 * Qualified Name:     com.qihoo.jiagu.e
 * JD-Core Version:    0.6.1
 */