package com.common.busi;

import java.util.ArrayList;

@QVMProtect
public final class a
{
  public ArrayList<e> a;
  private String b;

  // ERROR //
  public a(org.json.JSONObject paramJSONObject)
  {
    // Byte code:
    //   0: aload_0
    //   1: invokespecial 17	java/lang/Object:<init>	()V
    //   4: aload_0
    //   5: aconst_null
    //   6: putfield 19	com/common/busi/a:a	Ljava/util/ArrayList;
    //   9: aload_0
    //   10: aconst_null
    //   11: putfield 21	com/common/busi/a:b	Ljava/lang/String;
    //   14: aload_0
    //   15: aload_1
    //   16: ldc 23
    //   18: invokevirtual 29	org/json/JSONObject:optString	(Ljava/lang/String;)Ljava/lang/String;
    //   21: putfield 21	com/common/busi/a:b	Ljava/lang/String;
    //   24: aload_0
    //   25: getfield 21	com/common/busi/a:b	Ljava/lang/String;
    //   28: ifnonnull +4 -> 32
    //   31: return
    //   32: aload_0
    //   33: getfield 21	com/common/busi/a:b	Ljava/lang/String;
    //   36: ldc 31
    //   38: invokevirtual 37	java/lang/String:equals	(Ljava/lang/Object;)Z
    //   41: ifne -10 -> 31
    //   44: aload_0
    //   45: getfield 21	com/common/busi/a:b	Ljava/lang/String;
    //   48: ldc 39
    //   50: invokevirtual 37	java/lang/String:equals	(Ljava/lang/Object;)Z
    //   53: ifne -22 -> 31
    //   56: aload_0
    //   57: getfield 21	com/common/busi/a:b	Ljava/lang/String;
    //   60: ldc 41
    //   62: invokevirtual 37	java/lang/String:equals	(Ljava/lang/Object;)Z
    //   65: ifeq -34 -> 31
    //   68: aload_0
    //   69: new 43	java/util/ArrayList
    //   72: dup
    //   73: invokespecial 44	java/util/ArrayList:<init>	()V
    //   76: putfield 19	com/common/busi/a:a	Ljava/util/ArrayList;
    //   79: aload_1
    //   80: ldc 46
    //   82: invokevirtual 29	org/json/JSONObject:optString	(Ljava/lang/String;)Ljava/lang/String;
    //   85: astore_2
    //   86: new 48	java/io/StringReader
    //   89: dup
    //   90: aload_2
    //   91: invokespecial 51	java/io/StringReader:<init>	(Ljava/lang/String;)V
    //   94: astore_3
    //   95: new 53	android/util/JsonReader
    //   98: dup
    //   99: aload_3
    //   100: invokespecial 56	android/util/JsonReader:<init>	(Ljava/io/Reader;)V
    //   103: astore 4
    //   105: aload 4
    //   107: invokevirtual 59	android/util/JsonReader:beginArray	()V
    //   110: aload 4
    //   112: invokevirtual 63	android/util/JsonReader:hasNext	()Z
    //   115: ifeq +753 -> 868
    //   118: iconst_0
    //   119: istore 12
    //   121: new 65	com/common/busi/e
    //   124: dup
    //   125: invokespecial 66	com/common/busi/e:<init>	()V
    //   128: astore 13
    //   130: aload 4
    //   132: invokevirtual 69	android/util/JsonReader:beginObject	()V
    //   135: aload 4
    //   137: invokevirtual 63	android/util/JsonReader:hasNext	()Z
    //   140: ifeq +613 -> 753
    //   143: aload 4
    //   145: invokevirtual 73	android/util/JsonReader:nextName	()Ljava/lang/String;
    //   148: astore 15
    //   150: aload 15
    //   152: ldc 75
    //   154: invokevirtual 37	java/lang/String:equals	(Ljava/lang/Object;)Z
    //   157: ifeq +48 -> 205
    //   160: aload 13
    //   162: aload 4
    //   164: invokevirtual 79	android/util/JsonReader:nextInt	()I
    //   167: putfield 82	com/common/busi/e:a	I
    //   170: goto -35 -> 135
    //   173: astore 7
    //   175: aload 4
    //   177: astore 8
    //   179: aload_3
    //   180: astore 9
    //   182: aload 8
    //   184: ifnull +8 -> 192
    //   187: aload 8
    //   189: invokevirtual 85	android/util/JsonReader:close	()V
    //   192: aload 9
    //   194: ifnull -163 -> 31
    //   197: aload 9
    //   199: invokevirtual 86	java/io/StringReader:close	()V
    //   202: goto -171 -> 31
    //   205: aload 15
    //   207: ldc 88
    //   209: invokevirtual 37	java/lang/String:equals	(Ljava/lang/Object;)Z
    //   212: ifeq +505 -> 717
    //   215: aload 4
    //   217: invokevirtual 69	android/util/JsonReader:beginObject	()V
    //   220: aload 4
    //   222: invokevirtual 63	android/util/JsonReader:hasNext	()Z
    //   225: ifeq +210 -> 435
    //   228: aload 4
    //   230: invokevirtual 73	android/util/JsonReader:nextName	()Ljava/lang/String;
    //   233: astore 16
    //   235: aload 16
    //   237: ldc 89
    //   239: invokevirtual 37	java/lang/String:equals	(Ljava/lang/Object;)Z
    //   242: ifeq +62 -> 304
    //   245: new 43	java/util/ArrayList
    //   248: dup
    //   249: invokespecial 44	java/util/ArrayList:<init>	()V
    //   252: astore 17
    //   254: aload 17
    //   256: aload 4
    //   258: invokevirtual 92	android/util/JsonReader:nextString	()Ljava/lang/String;
    //   261: invokevirtual 95	java/util/ArrayList:add	(Ljava/lang/Object;)Z
    //   264: pop
    //   265: aload 13
    //   267: getfield 98	com/common/busi/e:b	Ljava/util/HashMap;
    //   270: ldc 89
    //   272: aload 17
    //   274: invokevirtual 104	java/util/HashMap:put	(Ljava/lang/Object;Ljava/lang/Object;)Ljava/lang/Object;
    //   277: pop
    //   278: goto -58 -> 220
    //   281: astore 5
    //   283: aload 4
    //   285: ifnull +8 -> 293
    //   288: aload 4
    //   290: invokevirtual 85	android/util/JsonReader:close	()V
    //   293: aload_3
    //   294: ifnull +7 -> 301
    //   297: aload_3
    //   298: invokevirtual 86	java/io/StringReader:close	()V
    //   301: aload 5
    //   303: athrow
    //   304: aload 16
    //   306: ldc 106
    //   308: invokevirtual 37	java/lang/String:equals	(Ljava/lang/Object;)Z
    //   311: ifeq +39 -> 350
    //   314: new 43	java/util/ArrayList
    //   317: dup
    //   318: invokespecial 44	java/util/ArrayList:<init>	()V
    //   321: astore 20
    //   323: aload 20
    //   325: aload 4
    //   327: invokevirtual 92	android/util/JsonReader:nextString	()Ljava/lang/String;
    //   330: invokevirtual 95	java/util/ArrayList:add	(Ljava/lang/Object;)Z
    //   333: pop
    //   334: aload 13
    //   336: getfield 98	com/common/busi/e:b	Ljava/util/HashMap;
    //   339: ldc 106
    //   341: aload 20
    //   343: invokevirtual 104	java/util/HashMap:put	(Ljava/lang/Object;Ljava/lang/Object;)Ljava/lang/Object;
    //   346: pop
    //   347: goto -127 -> 220
    //   350: aload 16
    //   352: ldc 75
    //   354: invokevirtual 37	java/lang/String:equals	(Ljava/lang/Object;)Z
    //   357: ifeq +39 -> 396
    //   360: new 43	java/util/ArrayList
    //   363: dup
    //   364: invokespecial 44	java/util/ArrayList:<init>	()V
    //   367: astore 23
    //   369: aload 23
    //   371: aload 4
    //   373: invokevirtual 92	android/util/JsonReader:nextString	()Ljava/lang/String;
    //   376: invokevirtual 95	java/util/ArrayList:add	(Ljava/lang/Object;)Z
    //   379: pop
    //   380: aload 13
    //   382: getfield 98	com/common/busi/e:b	Ljava/util/HashMap;
    //   385: ldc 75
    //   387: aload 23
    //   389: invokevirtual 104	java/util/HashMap:put	(Ljava/lang/Object;Ljava/lang/Object;)Ljava/lang/Object;
    //   392: pop
    //   393: goto -173 -> 220
    //   396: aload 16
    //   398: ldc 108
    //   400: invokevirtual 37	java/lang/String:equals	(Ljava/lang/Object;)Z
    //   403: ifeq +64 -> 467
    //   406: new 43	java/util/ArrayList
    //   409: dup
    //   410: invokespecial 44	java/util/ArrayList:<init>	()V
    //   413: astore 26
    //   415: aload 4
    //   417: invokevirtual 92	android/util/JsonReader:nextString	()Ljava/lang/String;
    //   420: astore 27
    //   422: aload 27
    //   424: ldc 110
    //   426: invokevirtual 37	java/lang/String:equals	(Ljava/lang/Object;)Z
    //   429: ifeq +14 -> 443
    //   432: iconst_1
    //   433: istore 12
    //   435: aload 4
    //   437: invokevirtual 113	android/util/JsonReader:endObject	()V
    //   440: goto -305 -> 135
    //   443: aload 26
    //   445: aload 27
    //   447: invokevirtual 95	java/util/ArrayList:add	(Ljava/lang/Object;)Z
    //   450: pop
    //   451: aload 13
    //   453: getfield 98	com/common/busi/e:b	Ljava/util/HashMap;
    //   456: ldc 108
    //   458: aload 26
    //   460: invokevirtual 104	java/util/HashMap:put	(Ljava/lang/Object;Ljava/lang/Object;)Ljava/lang/Object;
    //   463: pop
    //   464: goto -244 -> 220
    //   467: aload 16
    //   469: ldc 115
    //   471: invokevirtual 37	java/lang/String:equals	(Ljava/lang/Object;)Z
    //   474: ifeq +60 -> 534
    //   477: new 43	java/util/ArrayList
    //   480: dup
    //   481: invokespecial 44	java/util/ArrayList:<init>	()V
    //   484: astore 30
    //   486: aload 4
    //   488: invokevirtual 59	android/util/JsonReader:beginArray	()V
    //   491: aload 4
    //   493: invokevirtual 63	android/util/JsonReader:hasNext	()Z
    //   496: ifeq +17 -> 513
    //   499: aload 30
    //   501: aload 4
    //   503: invokevirtual 92	android/util/JsonReader:nextString	()Ljava/lang/String;
    //   506: invokevirtual 95	java/util/ArrayList:add	(Ljava/lang/Object;)Z
    //   509: pop
    //   510: goto -19 -> 491
    //   513: aload 4
    //   515: invokevirtual 118	android/util/JsonReader:endArray	()V
    //   518: aload 13
    //   520: getfield 98	com/common/busi/e:b	Ljava/util/HashMap;
    //   523: ldc 115
    //   525: aload 30
    //   527: invokevirtual 104	java/util/HashMap:put	(Ljava/lang/Object;Ljava/lang/Object;)Ljava/lang/Object;
    //   530: pop
    //   531: goto -311 -> 220
    //   534: aload 16
    //   536: ldc 120
    //   538: invokevirtual 37	java/lang/String:equals	(Ljava/lang/Object;)Z
    //   541: ifeq +42 -> 583
    //   544: new 43	java/util/ArrayList
    //   547: dup
    //   548: invokespecial 44	java/util/ArrayList:<init>	()V
    //   551: astore 33
    //   553: aload 33
    //   555: aload 4
    //   557: invokevirtual 79	android/util/JsonReader:nextInt	()I
    //   560: invokestatic 124	java/lang/String:valueOf	(I)Ljava/lang/String;
    //   563: invokevirtual 95	java/util/ArrayList:add	(Ljava/lang/Object;)Z
    //   566: pop
    //   567: aload 13
    //   569: getfield 98	com/common/busi/e:b	Ljava/util/HashMap;
    //   572: ldc 120
    //   574: aload 33
    //   576: invokevirtual 104	java/util/HashMap:put	(Ljava/lang/Object;Ljava/lang/Object;)Ljava/lang/Object;
    //   579: pop
    //   580: goto -360 -> 220
    //   583: aload 16
    //   585: ldc 126
    //   587: invokevirtual 37	java/lang/String:equals	(Ljava/lang/Object;)Z
    //   590: ifeq +60 -> 650
    //   593: new 43	java/util/ArrayList
    //   596: dup
    //   597: invokespecial 44	java/util/ArrayList:<init>	()V
    //   600: astore 36
    //   602: aload 4
    //   604: invokevirtual 59	android/util/JsonReader:beginArray	()V
    //   607: aload 4
    //   609: invokevirtual 63	android/util/JsonReader:hasNext	()Z
    //   612: ifeq +17 -> 629
    //   615: aload 36
    //   617: aload 4
    //   619: invokevirtual 92	android/util/JsonReader:nextString	()Ljava/lang/String;
    //   622: invokevirtual 95	java/util/ArrayList:add	(Ljava/lang/Object;)Z
    //   625: pop
    //   626: goto -19 -> 607
    //   629: aload 4
    //   631: invokevirtual 118	android/util/JsonReader:endArray	()V
    //   634: aload 13
    //   636: getfield 98	com/common/busi/e:b	Ljava/util/HashMap;
    //   639: ldc 126
    //   641: aload 36
    //   643: invokevirtual 104	java/util/HashMap:put	(Ljava/lang/Object;Ljava/lang/Object;)Ljava/lang/Object;
    //   646: pop
    //   647: goto -427 -> 220
    //   650: aload 16
    //   652: ldc 128
    //   654: invokevirtual 37	java/lang/String:equals	(Ljava/lang/Object;)Z
    //   657: ifeq +283 -> 940
    //   660: new 43	java/util/ArrayList
    //   663: dup
    //   664: invokespecial 44	java/util/ArrayList:<init>	()V
    //   667: astore 39
    //   669: aload 4
    //   671: invokevirtual 59	android/util/JsonReader:beginArray	()V
    //   674: aload 4
    //   676: invokevirtual 63	android/util/JsonReader:hasNext	()Z
    //   679: ifeq +17 -> 696
    //   682: aload 39
    //   684: aload 4
    //   686: invokevirtual 92	android/util/JsonReader:nextString	()Ljava/lang/String;
    //   689: invokevirtual 95	java/util/ArrayList:add	(Ljava/lang/Object;)Z
    //   692: pop
    //   693: goto -19 -> 674
    //   696: aload 4
    //   698: invokevirtual 118	android/util/JsonReader:endArray	()V
    //   701: aload 13
    //   703: getfield 98	com/common/busi/e:b	Ljava/util/HashMap;
    //   706: ldc 128
    //   708: aload 39
    //   710: invokevirtual 104	java/util/HashMap:put	(Ljava/lang/Object;Ljava/lang/Object;)Ljava/lang/Object;
    //   713: pop
    //   714: goto -494 -> 220
    //   717: aload 15
    //   719: ldc 130
    //   721: invokevirtual 37	java/lang/String:equals	(Ljava/lang/Object;)Z
    //   724: ifeq +52 -> 776
    //   727: aload 13
    //   729: aload 4
    //   731: invokevirtual 92	android/util/JsonReader:nextString	()Ljava/lang/String;
    //   734: putfield 133	com/common/busi/e:c	Ljava/lang/String;
    //   737: aload 13
    //   739: getfield 133	com/common/busi/e:c	Ljava/lang/String;
    //   742: ldc 110
    //   744: invokevirtual 37	java/lang/String:equals	(Ljava/lang/Object;)Z
    //   747: ifeq -612 -> 135
    //   750: iconst_1
    //   751: istore 12
    //   753: aload 4
    //   755: invokevirtual 113	android/util/JsonReader:endObject	()V
    //   758: iload 12
    //   760: ifne -650 -> 110
    //   763: aload_0
    //   764: getfield 19	com/common/busi/a:a	Ljava/util/ArrayList;
    //   767: aload 13
    //   769: invokevirtual 95	java/util/ArrayList:add	(Ljava/lang/Object;)Z
    //   772: pop
    //   773: goto -663 -> 110
    //   776: aload 15
    //   778: ldc 135
    //   780: invokevirtual 37	java/lang/String:equals	(Ljava/lang/Object;)Z
    //   783: ifeq +16 -> 799
    //   786: aload 13
    //   788: aload 4
    //   790: invokevirtual 79	android/util/JsonReader:nextInt	()I
    //   793: putfield 137	com/common/busi/e:d	I
    //   796: goto -661 -> 135
    //   799: aload 15
    //   801: ldc 139
    //   803: invokevirtual 37	java/lang/String:equals	(Ljava/lang/Object;)Z
    //   806: ifeq +16 -> 822
    //   809: aload 13
    //   811: aload 4
    //   813: invokevirtual 79	android/util/JsonReader:nextInt	()I
    //   816: putfield 142	com/common/busi/e:e	I
    //   819: goto -684 -> 135
    //   822: aload 15
    //   824: ldc 144
    //   826: invokevirtual 37	java/lang/String:equals	(Ljava/lang/Object;)Z
    //   829: ifeq +16 -> 845
    //   832: aload 13
    //   834: aload 4
    //   836: invokevirtual 92	android/util/JsonReader:nextString	()Ljava/lang/String;
    //   839: putfield 146	com/common/busi/e:f	Ljava/lang/String;
    //   842: goto -707 -> 135
    //   845: aload 15
    //   847: ldc 148
    //   849: invokevirtual 37	java/lang/String:equals	(Ljava/lang/Object;)Z
    //   852: ifeq +94 -> 946
    //   855: aload 13
    //   857: aload 4
    //   859: invokevirtual 92	android/util/JsonReader:nextString	()Ljava/lang/String;
    //   862: putfield 151	com/common/busi/e:g	Ljava/lang/String;
    //   865: goto -730 -> 135
    //   868: aload 4
    //   870: invokevirtual 118	android/util/JsonReader:endArray	()V
    //   873: aload 4
    //   875: invokevirtual 85	android/util/JsonReader:close	()V
    //   878: aload_3
    //   879: invokevirtual 86	java/io/StringReader:close	()V
    //   882: goto -851 -> 31
    //   885: astore 11
    //   887: goto -9 -> 878
    //   890: astore 10
    //   892: goto -700 -> 192
    //   895: astore 6
    //   897: goto -604 -> 293
    //   900: astore 5
    //   902: aconst_null
    //   903: astore 4
    //   905: aconst_null
    //   906: astore_3
    //   907: goto -624 -> 283
    //   910: astore 5
    //   912: aconst_null
    //   913: astore 4
    //   915: goto -632 -> 283
    //   918: astore 43
    //   920: aconst_null
    //   921: astore 8
    //   923: aconst_null
    //   924: astore 9
    //   926: goto -744 -> 182
    //   929: astore 42
    //   931: aload_3
    //   932: astore 9
    //   934: aconst_null
    //   935: astore 8
    //   937: goto -755 -> 182
    //   940: iconst_1
    //   941: istore 12
    //   943: goto -723 -> 220
    //   946: iconst_1
    //   947: istore 12
    //   949: goto -814 -> 135
    //
    // Exception table:
    //   from	to	target	type
    //   105	170	173	java/io/IOException
    //   205	278	173	java/io/IOException
    //   304	873	173	java/io/IOException
    //   105	170	281	finally
    //   205	278	281	finally
    //   304	873	281	finally
    //   873	878	885	java/io/IOException
    //   187	192	890	java/io/IOException
    //   288	293	895	java/io/IOException
    //   86	95	900	finally
    //   95	105	910	finally
    //   86	95	918	java/io/IOException
    //   95	105	929	java/io/IOException
  }
}

/* Location:           C:\Users\bbbff\Desktop\onekey-decompile-apk\_tools\dex2jar\source-3125444_dex2jar.jar
 * Qualified Name:     com.common.busi.a
 * JD-Core Version:    0.6.1
 */